liquidnet/__init__.py
liquidnet/main.py
liquidnet/vision_liquidnet.py
liquidnet-0.0.5.dist-info/LICENSE
liquidnet-0.0.5.dist-info/WHEEL
liquidnet-0.0.5.dist-info/METADATA
liquidnet-0.0.5.dist-info/RECORD
